{
  "project_info": {
    "project_number": "426778137133",
    "firebase_url": "https://generation-33ad3-default-rtdb.firebaseio.com",
    "project_id": "generation-33ad3",
    "storage_bucket": "generation-33ad3.appspot.com"
  },
  "client": [
    {
      "client_info": {
        "mobilesdk_app_id": "1:426778137133:android:b0638f094e8b8030911ea4",
        "android_client_info": {
          "package_name": "com.anoop.karan.generation"
        }
      },
      "oauth_client": [
        {
          "client_id": "426778137133-bha3fcgnerlanej8mmo0nodp7q6r2kgh.apps.googleusercontent.com",
          "client_type": 1,
          "android_info": {
            "package_name": "com.anoop.karan.generation",
            "certificate_hash": "f2e42508b81d465e5cfc90fead0c5ee15658a58e"
          }
        },
        {
          "client_id": "426778137133-ecbqll393dpv0ujg7nlfgblqco28bkbv.apps.googleusercontent.com",
          "client_type": 3
        }
      ],
      "api_key": [
        {
          "current_key": "AIzaSyCBgcLv8xkw5T-15twzI-kd1m2HzQycuE8"
        }
      ],
      "services": {
        "appinvite_service": {
          "other_platform_oauth_client": [
            {
              "client_id": "426778137133-ecbqll393dpv0ujg7nlfgblqco28bkbv.apps.googleusercontent.com",
              "client_type": 3
            }
          ]
        }
      }
    }
  ],
  "configuration_version": "1"
}